pykali/__init__.py
pykali/kali.py
pykali/modules/bands.py
pykali/modules/genome.py
pykali/modules/genomeset.py
pykali-1.5.0.dist-info/METADATA
pykali-1.5.0.dist-info/WHEEL
pykali-1.5.0.dist-info/entry_points.txt
pykali-1.5.0.dist-info/licenses/LICENSE
pykali-1.5.0.dist-info/RECORD
